CHANGES.rst
CONTRIBUTORS.rst
MANIFEST.in
README.rst
setup.cfg
setup.py
docs/LICENSE.GPL
docs/LICENSE.rst
docs/index.rst
docs/readthedocs-requirements.txt
docs/_images/setup_select_add_on.png
docs/_images/setup_select_add_on_installable.png
docs/source/conf.py
docs/source/configuration.rst
docs/source/index.rst
docs/source/_static/.gitkeep
docs/source/_static/logo.png
docs/source/_templates/.gitkeep
src/collective/__init__.py
src/collective.tiles.githubgist.egg-info/PKG-INFO
src/collective.tiles.githubgist.egg-info/SOURCES.txt
src/collective.tiles.githubgist.egg-info/dependency_links.txt
src/collective.tiles.githubgist.egg-info/entry_points.txt
src/collective.tiles.githubgist.egg-info/namespace_packages.txt
src/collective.tiles.githubgist.egg-info/not-zip-safe
src/collective.tiles.githubgist.egg-info/requires.txt
src/collective.tiles.githubgist.egg-info/top_level.txt
src/collective/tiles/__init__.py
src/collective/tiles/githubgist/__init__.py
src/collective/tiles/githubgist/config.py
src/collective/tiles/githubgist/configure.zcml
src/collective/tiles/githubgist/interfaces.py
src/collective/tiles/githubgist/setuphandlers.py
src/collective/tiles/githubgist/testing.py
src/collective/tiles/githubgist/tile.pt
src/collective/tiles/githubgist/tile.py
src/collective/tiles/githubgist/browser/__init__.py
src/collective/tiles/githubgist/browser/configure.zcml
src/collective/tiles/githubgist/browser/static/.gitkeep
src/collective/tiles/githubgist/locales/collective.tiles.githubgist.pot
src/collective/tiles/githubgist/locales/update.sh
src/collective/tiles/githubgist/profiles/default/browserlayer.xml
src/collective/tiles/githubgist/profiles/default/metadata.xml
src/collective/tiles/githubgist/profiles/default/registry.xml
src/collective/tiles/githubgist/profiles/mosaic_support/registry.xml
src/collective/tiles/githubgist/profiles/uninstall/browserlayer.xml
src/collective/tiles/githubgist/tests/__init__.py
src/collective/tiles/githubgist/tests/test_robot.py
src/collective/tiles/githubgist/tests/test_setup.py
src/collective/tiles/githubgist/tests/test_tile.py
src/collective/tiles/githubgist/tests/robot/keywords.robot
src/collective/tiles/githubgist/tests/robot/test_setup.robot