Metadata-Version: 1.1
Name: collective.tiles.githubgist
Version: 0.1
Summary: A tile that shows Gists from GitHub.
Home-page: https://github.com/it-spirit/collective.tiles.githubgist
Author: it-spirit
Author-email: thomas.massmann@it-spir.it
License: GPL version 2
Download-URL: https://pypi.python.org/pypi/collective.tiles.githubgist
Keywords: Python Plone
Platform: UNKNOWN
Classifier: Development Status :: 4 - Beta
Classifier: Environment :: Web Environment
Classifier: Framework :: Plone
Classifier: Framework :: Plone
Classifier: Framework :: Plone :: 5.0
Classifier: Framework :: Plone :: 5.1
Classifier: License :: OSI Approved :: GNU General Public License v2 (GPLv2)
Classifier: Operating System :: OS Independent
Classifier: Programming Language :: Python
Classifier: Programming Language :: Python :: 2.7
